<?xml version="1.0" encoding="UTF-8"?><record_update table="sc_cat_item_catalog">
    <sc_cat_item_catalog action="INSERT_OR_UPDATE">
        <sc_cat_item display_value="Place new order">f9c55afbc3302210258ad4fc050131ea</sc_cat_item>
        <sc_catalog display_value="Service Catalog">e0d08b13c3330100c8b837659bba8fb4</sc_catalog>
        <sys_class_name>sc_cat_item_catalog</sys_class_name>
        <sys_created_by>admin</sys_created_by>
        <sys_created_on>2025-04-16 06:56:48</sys_created_on>
        <sys_id>3ec0a2fbc3702210258ad4fc05013157</sys_id>
        <sys_mod_count>0</sys_mod_count>
        <sys_name>Service Catalog.Place new order</sys_name>
        <sys_package display_value="Ecommerce" source="x_1585559_ecommerc">185db557c3a02210258ad4fc050131ce</sys_package>
        <sys_policy/>
        <sys_scope display_value="Ecommerce">185db557c3a02210258ad4fc050131ce</sys_scope>
        <sys_update_name>sc_cat_item_catalog_3ec0a2fbc3702210258ad4fc05013157</sys_update_name>
        <sys_updated_by>admin</sys_updated_by>
        <sys_updated_on>2025-04-16 06:56:48</sys_updated_on>
    </sc_cat_item_catalog>
</record_update>
